ai_pr_insight/__init__.py
ai_pr_insight/analyzer.py
ai_pr_insight/cli.py
ai_pr_insight/config.py
ai_pr_insight/diagnostic.py
ai_pr_insight/fetcher.py
ai_pr_insight/summarizer.py
ai_pr_insight/utils.py
ai_pr_insight-1.2.0.dist-info/LICENSE
ai_pr_insight-1.2.0.dist-info/METADATA
ai_pr_insight-1.2.0.dist-info/WHEEL
ai_pr_insight-1.2.0.dist-info/entry_points.txt
ai_pr_insight-1.2.0.dist-info/top_level.txt
ai_pr_insight-1.2.0.dist-info/RECORD
