Metadata-Version: 2.2
Name: ai-pr-insight
Version: 1.2.0
Summary: A tool to analyze GitHub PR comments and generate actionable insights using AI.
Home-page: https://github.com/kadivar/ai-pr-insight
Author: Mohammadreza Kadivar
Author-email: me.kadivar@gmail.com
License: GNU AGPL
Project-URL: Source, https://github.com/kadivar/ai-pr-insight
Project-URL: Bug Reports, https://github.com/kadivar/ai-pr-insight/issues
Keywords: github,pull-requests,code-review,ai,openai
Classifier: Development Status :: 4 - Beta
Classifier: Intended Audience :: Developers
Classifier: License :: OSI Approved :: GNU Affero General Public License v3
Classifier: Programming Language :: Python :: 3
Classifier: Programming Language :: Python :: 3.8
Classifier: Programming Language :: Python :: 3.9
Classifier: Programming Language :: Python :: 3.10
Classifier: Programming Language :: Python :: 3.11
Classifier: Topic :: Software Development :: Version Control :: Git
Classifier: Topic :: Software Development :: Quality Assurance
Requires-Python: >=3.8
License-File: LICENSE
Requires-Dist: requests>=2.30.0
Requires-Dist: python-dotenv>=1.0.0
Requires-Dist: openai>=1.3.0
Requires-Dist: tqdm>=4.65.0
Requires-Dist: numpy>=1.24.0
Requires-Dist: scikit-learn>=1.2.0
Requires-Dist: python-dateutil>=2.8.0
Requires-Dist: tiktoken>=0.5.0
Dynamic: author
Dynamic: author-email
Dynamic: classifier
Dynamic: description
Dynamic: description-content-type
Dynamic: home-page
Dynamic: keywords
Dynamic: license
Dynamic: project-url
Dynamic: requires-dist
Dynamic: requires-python
Dynamic: summary
